<?xml version="1.0"?>
<?mso-application progid="Excel.Sheet"?>
<!-- 
Copyright (c) 2015 EXILANT Technologies Private Limited

Permission is hereby granted, free of charge, to any person obtaining a copy
of this software and associated documentation files (the "Software"), to deal
in the Software without restriction, including without limitation the rights
to use, copy, modify, merge, publish, distribute, sublicense, and/or sell
copies of the Software, and to permit persons to whom the Software is
furnished to do so, subject to the following conditions:

The above copyright notice and this permission notice shall be included in
all copies or substantial portions of the Software.

THE SOFTWARE IS PROVIDED "AS IS", WITHOUT WARRANTY OF ANY KIND, EXPRESS OR
IMPLIED, INCLUDING BUT NOT LIMITED TO THE WARRANTIES OF MERCHANTABILITY,
FITNESS FOR A PARTICULAR PURPOSE AND NONINFRINGEMENT. IN NO EVENT SHALL THE
AUTHORS OR COPYRIGHT HOLDERS BE LIABLE FOR ANY CLAIM, DAMAGES OR OTHER
LIABILITY, WHETHER IN AN ACTION OF CONTRACT, TORT OR OTHERWISE, ARISING FROM,
OUT OF OR IN CONNECTION WITH THE SOFTWARE OR THE USE OR OTHER DEALINGS IN
THE SOFTWARE.
 -->
<Workbook xmlns="urn:schemas-microsoft-com:office:spreadsheet"
 xmlns:o="urn:schemas-microsoft-com:office:office"
 xmlns:x="urn:schemas-microsoft-com:office:excel"
 xmlns:ss="urn:schemas-microsoft-com:office:spreadsheet"
 xmlns:html="http://www.w3.org/TR/REC-html40">
 <DocumentProperties xmlns="urn:schemas-microsoft-com:office:office">
  <Author>RG Bhandi</Author>
  <LastAuthor>RG Bhandi</LastAuthor>
  <Created>2013-01-17T05:03:55Z</Created>
  <LastSaved>2013-01-17T17:17:57Z</LastSaved>
  <Version>12.00</Version>
 </DocumentProperties>
 <ExcelWorkbook xmlns="urn:schemas-microsoft-com:office:excel">
  <WindowHeight>7995</WindowHeight>
  <WindowWidth>20115</WindowWidth>
  <WindowTopX>240</WindowTopX>
  <WindowTopY>120</WindowTopY>
  <ActiveSheet>1</ActiveSheet>
  <ProtectStructure>False</ProtectStructure>
  <ProtectWindows>False</ProtectWindows>
 </ExcelWorkbook>
 <Styles>
  <Style ss:ID="Default" ss:Name="Normal">
   <Alignment ss:Vertical="Bottom"/>
   <Borders/>
   <Font ss:FontName="Calibri" x:Family="Swiss" ss:Size="11" ss:Color="#000000"/>
   <Interior/>
   <NumberFormat/>
   <Protection/>
  </Style>
  <Style ss:ID="s62">
   <Font ss:FontName="Calibri" x:Family="Swiss" ss:Size="11" ss:Color="#FFFF00"/>
   <Interior ss:Color="#0070C0" ss:Pattern="Solid"/>
  </Style>
  <Style ss:ID="s63">
   <Alignment ss:Vertical="Center"/>
  </Style>
  <Style ss:ID="s64">
   <NumberFormat ss:Format="Medium Date"/>
  </Style>
 </Styles>
 <Worksheet ss:Name="controlSheet">
  <Table ss:ExpandedColumnCount="2" ss:ExpandedRowCount="7" x:FullColumns="1"
   x:FullRows="1" ss:DefaultRowHeight="15">
   <Column ss:Width="118.5"/>
   <Column ss:Width="582"/>
   <Row ss:AutoFitHeight="0">
    <Cell ss:StyleID="s62"><Data ss:Type="String">name</Data></Cell>
    <Cell ss:StyleID="s62"><Data ss:Type="String">value</Data></Cell>
   </Row>
   <Row ss:AutoFitHeight="0">
    <Cell ss:StyleID="s62"><Data ss:Type="String">Started at</Data></Cell>
    <Cell ss:StyleID="s62"/>
   </Row>
   <Row ss:StyleID="s63">
    <Cell><Data ss:Type="String">Completed at</Data></Cell>
   </Row>
   <Row ss:AutoFitHeight="0">
    <Cell><Data ss:Type="String">Total components</Data></Cell>
   </Row>
   <Row ss:AutoFitHeight="0">
    <Cell><Data ss:Type="String">Total test cases</Data></Cell>
   </Row>
   <Row ss:AutoFitHeight="0">
    <Cell><Data ss:Type="String">total failed components</Data></Cell>
   </Row>
   <Row ss:AutoFitHeight="0">
    <Cell><Data ss:Type="String">total failed test cases</Data></Cell>
   </Row>
  </Table>
  <WorksheetOptions xmlns="urn:schemas-microsoft-com:office:excel">
   <PageSetup>
    <Header x:Margin="0.3"/>
    <Footer x:Margin="0.3"/>
    <PageMargins x:Bottom="0.75" x:Left="0.7" x:Right="0.7" x:Top="0.75"/>
   </PageSetup>
   <Unsynced/>
   <Print>
    <ValidPrinterInfo/>
    <HorizontalResolution>600</HorizontalResolution>
    <VerticalResolution>600</VerticalResolution>
   </Print>
   <FreezePanes/>
   <FrozenNoSplit/>
   <SplitHorizontal>1</SplitHorizontal>
   <TopRowBottomPane>1</TopRowBottomPane>
   <ActivePane>2</ActivePane>
   <Panes>
    <Pane>
     <Number>3</Number>
    </Pane>
    <Pane>
     <Number>2</Number>
     <ActiveRow>0</ActiveRow>
     <ActiveCol>2</ActiveCol>
    </Pane>
   </Panes>
   <ProtectObjects>False</ProtectObjects>
   <ProtectScenarios>False</ProtectScenarios>
  </WorksheetOptions>
 </Worksheet>
 <Worksheet ss:Name="result">
  <Table ss:ExpandedColumnCount="9" ss:ExpandedRowCount="3" x:FullColumns="1"
   x:FullRows="1" ss:DefaultRowHeight="15">
   <Column ss:AutoFitWidth="0" ss:Width="95.25"/>
   <Column ss:Width="183"/>
   <Column ss:Width="48.75"/>
   <Column ss:Index="5" ss:Width="42.75"/>
   <Column ss:Width="73.5"/>
   <Column ss:Width="60"/>
   <Column ss:Width="106.5"/>
   <Column ss:AutoFitWidth="0" ss:Width="168"/>
   <Row ss:AutoFitHeight="0">
    <Cell ss:StyleID="s62"><Data ss:Type="String">Component Type</Data></Cell>
    <Cell ss:StyleID="s62"><Data ss:Type="String">component Name</Data></Cell>
    <Cell ss:StyleID="s62"><Data ss:Type="String">Test Case</Data></Cell>
    <Cell ss:StyleID="s62"><Data ss:Type="String">Description</Data></Cell>
    <Cell ss:StyleID="s62"><Data ss:Type="String">Passed?</Data></Cell>
    <Cell ss:StyleID="s62"><Data ss:Type="String">expected time</Data></Cell>
    <Cell ss:StyleID="s62"><Data ss:Type="String">Actual Time</Data></Cell>
    <Cell ss:StyleID="s62"><Data ss:Type="String">Passed Performance?</Data></Cell>
    <Cell ss:StyleID="s62"><Data ss:Type="String">Failure reason</Data></Cell>
   </Row>
   <Row ss:AutoFitHeight="0" ss:StyleID="s63"/>
   <Row ss:AutoFitHeight="0">
    <Cell ss:Index="2" ss:StyleID="s64"/>
   </Row>
  </Table>
  <WorksheetOptions xmlns="urn:schemas-microsoft-com:office:excel">
   <PageSetup>
    <Header x:Margin="0.3"/>
    <Footer x:Margin="0.3"/>
    <PageMargins x:Bottom="0.75" x:Left="0.7" x:Right="0.7" x:Top="0.75"/>
   </PageSetup>
   <Unsynced/>
   <Selected/>
   <ProtectObjects>False</ProtectObjects>
   <ProtectScenarios>False</ProtectScenarios>
  </WorksheetOptions>
 </Worksheet>
</Workbook>
